flask_appconfigure/__init__.py
flask_appconfigure/base_configurator.py
flask_appconfigure/exceptions.py
flask_appconfigure/factory.py
flask_appconfigure-1.0.1.dist-info/LICENSE
flask_appconfigure-1.0.1.dist-info/METADATA
flask_appconfigure-1.0.1.dist-info/WHEEL
flask_appconfigure-1.0.1.dist-info/top_level.txt
flask_appconfigure-1.0.1.dist-info/RECORD
