Metadata-Version: 2.1
Name: flask-appconfigure
Version: 1.0.1
Summary: Flask Application Configurator
Home-page: https://github.com/tibotix/flask_appconfigure
Author: Tibotix
Author-email: tizian@seehaus.net
Requires-Python: >=3.7, <4
License-File: LICENSE
Requires-Dist: flask
Provides-Extra: test
Requires-Dist: pytest ; extra == 'test'
